Workbook

Sheet Pre-Acquisition
B2: Presario Ventures (Pre-Acquisition) | D2: Given Information | F2: QUESTION # 2
F3: (Pre-Acquisition) Balance Sheet | H3: Equation
B4: Capital Structure
B5: Equity % | C5: 1 | F5: Assets
B6: Debt % | C6: 0 | F6: Total Assets | G6: =G13+G9 -> 308800000 | H6: Liabilities + Equity
F7: =
B8: Firm Information | F8: Liabilities
B9: Common Stock Outstandng | C9: 8000000 | F9: Total Debt | G9: 0 | H9: No Use of Debt
B10: Market Price of Stock | C10: 38.6 | F10: +
B11: Corporate Tax Rate (State+Fed) | C11: 0.25 | F11: Equity
B12: Cost of Capital (Unlevered) | C12: 0.097 | F12: Common Stock | G12: =C9*C10 -> 308800000 | H12: Shares Outstanding * Price
F13: Total Equity | G13: =G12 -> 308800000

Sheet Acquisition Info
B2: QUESTION # 3a | F2: QUESTION # 1
B3: Aquisitoin Information + Valuation | D3: Given Info or Equatoin | F3: Target Capital Structure | H3: Given Info or Equatoin
B5: Aquisitoin Price | C5: 27000000 | D5: Given | F5: Target Equity % | G5: 0.65 | H5: Given
B6: Pre-Tax Cash Flows (Annual) | C6: 4500000 | D6: Given | F6: Target Debt % | G6: 0.35 | H6: Given
B7: After-Tax Cash Flows (Annual) | C7: =C6*(1-'Pre-Acquisition'!C11) -> 3375000 | D7: Pretax*(1-Tax)
B8: Cash Flow Duratoin | C8: Perpituity | D8: Given | F8: QUESTION # 1
B9: PV of Perpetuity | C9: =C7/'Pre-Acquisition'!C12 -> 34793814 | D9: After-Tax/Rate | F9: Capital Structure If 100% Debt Financed | H9: Equation
B10: NPV of Acquisition | C10: =C9-C5 -> 7793814.4 | D10: PV - Price
F11: Equity % | G11: =1-G12 -> 0.919595 | H11: 1-debt
B12: Comparable Debt Information | D12: Given Info or Equatoin | F12: Debt % | G12: =C5/('Pre-Acquisition'!G13+C5) -> 0.080405003 | H12: price/(equity + price)
B14: Comparable Bond Price | C14: 935.74 | D14: Given
B15: Par Value | C15: 1000 | D15: Given
B16: Coupon Rate | C16: 0.045 | D16: Given
B17: Coupon Frequency | C17: Semiannual | D17: Given
B18: Original Maturity | C18: 10 | D18: Given
B19: Years Remaining | C19: 5 | D19: Given
B20: PMT Frequency | C20: Semiannual | D20: Given
B21: Periods Remaining | C21: =C19*2 -> 10 | D21: yrs remaining * 2
B22: Coupon PMT | C22: =(C15*C16)/2 -> 22.5 | D22: (par*cr)/2
B23: Yield to Maturity | C23: =(RATE(C21,C22,-C14,C15))*2 -> 0.060069122 | D23: RATE function * 2

Sheet 100% Equity Finance
B2: QUESTION # 3b | F2: QUESTION # 3c
B3: 100% Equity Balance Sheet (Post Announcement) | D3: Equation | F3: 100% Equity Balance Sheet (Post Issuance) | H3: Equation
B5: Assets | F5: Assets
B6: Operating Assets | C6: =C14+C10 -> 3.1659381e+08 | D6: Liabilities + Equity | F6: Operating Assets | G6: =G14+G10 -> 3.3580003e+08 | H6: Liabilities + Equity
B7: Total Assets | C7: =C14+C10 -> 3.1659381e+08 | F7: Total Assets | G7: =G6 -> 3.3580003e+08
B8: = | F8: =
B9: Liabilities | F9: Liabilities
B10: Total Debt | C10: 0 | D10: No Use of Debt | F10: Total Debt | G10: 0 | H10: No Use of Debt
B11: + | F11: +
B12: Equity | F12: Equity
B13: Common Stock | C13: ='Pre-Acquisition'!G13+'Acquisition Info'!C10 -> 3.1659381e+08 | D13: Old Equity + Acquisition NPV | F13: Common Stock | G13: ='Pre-Acquisition'!G13+(C21*C20) -> 3.3580003e+08 | H13: Old Equity + (New Shares * Share Price)
B14: Total Equity | C14: =C13 -> 3.1659381e+08 | F14: Total Equity | G14: =G13 -> 3.3580003e+08
B16: QUESTION # 3b | F16: QUESTION # 3c
B17: 100% Equity Finance Stock (Post Announcement) | D17: Equation | F17: 100% Equity Finance Stock (Post Issuance) | H17: Equation
B19: Number of Shares Outstanding | C19: ='Pre-Acquisition'!C9 -> 8000000 | D19: Same Because its Pre Issuance | F19: Number of Shares Outstanding | G19: =C19+C21 -> 8682263 | H19: Old Shares + Newly Issued
B20: New Price Per Share | C20: =C14/C19 -> 39.574227 | D20: New Equity/# of Shares | F20: New Price Per Share | G20: =G14/G19 -> 38.676556 | H20: New Equity/New# of Shares
B21: New Shares Required for Equity Finance | C21: =ROUNDUP('Acquisition Info'!C5/C20,0) -> 682263 | D21: Roundup Functoin Acquisition Cost/New Share Price
B25: QUESTION # 3d
B26: 100% Equity Balance Sheet (Post Acquisition) | D26: Equation
B28: Assets
B29: Operating Assets | C29: ='Pre-Acquisition'!G13+'Acquisition Info'!C10 -> 3.1659381e+08 | D29: Equity
B30: Real Estate | C30: ='Acquisition Info'!C5 -> 27000000 | D30: Acquisition Cost
B31: Total Assets | C31: =C29+C30 -> 3.4359381e+08
B32: =
B33: Liabilities
B34: Total Debt | C34: 0 | D34: No Use of Debt
B35: +
B36: Equity
B37: Common Stock | C37: ='Pre-Acquisition'!G13+'Acquisition Info'!C10+'Acquisition Info'!C5 -> 3.4359381e+08 | D37: Old Equity + Acquisition Cost +NPV
B38: Total Equity | C38: =C37 -> 3.4359381e+08
B40: QUESTION # 3d
B41: 100% Equity Finance Stock (Post Acquisition) | D41: Equation
B43: Number of Shares Outstanding | C43: =C19+C21 -> 8682263 | D43: Old Shares + Newly Issued
B44: New Price Per Share | C44: =C38/C43 -> 39.574223 | D44: New Equity/# of Shares

Sheet 100% Debt Finance
B2: QUESTION # 4a | F2: QUESTION # 4b
B3: MV of Firm with 100% Debt Finance (Post Acquisition) | D3: Equation | F3: 100% Debt Balance Sheet (Post Acquisition) | H3: Equation
B5: Tax Shield | C5: ='Pre-Acquisition'!C11*'Acquisition Info'!C5 -> 6750000 | D5: Tax * Debt | F5: Assets
B6: Firm MV | C6: ='Acquisition Info'!C9+'Pre-Acquisition'!G12+'100% Debt Finance'!C5 -> 3.5034381e+08 | D6: Old MV + PV of Perpituity + tax Shield | F6: Operating Assets | G6: =G15 -> 3.2334381e+08 | H6: Equity
F7: Real Estate | G7: ='Acquisition Info'!C5 -> 27000000 | H7: Acquisition Cost
F8: Total Assets | G8: =G6+G7 -> 3.5034381e+08
F9: =
B10: QUESTION # 4c | F10: Liabilities
B11: WACC and Cost of Equity | D11: Equation | F11: Total Debt | G11: ='Acquisition Info'!C5 -> 27000000 | H11: Acquisition Price
F12: +
B13: Ru | C13: ='Pre-Acquisition'!C12 -> 0.097 | D13: Unlevered cost of capital | F13: Equity
B14: Rd | C14: ='Acquisition Info'!C23 -> 0.060069122 | D14: Cost of debt | F14: Common Stock | G14: =C6-'Acquisition Info'!C5 -> 3.2334381e+08 | H14: Firm MV - Acquisition Price
B15: D | C15: ='Acquisition Info'!C5 -> 27000000 | D15: Debt | F15: Total Equity | G15: =G14 -> 3.2334381e+08
B16: E | C16: =G15 -> 3.2334381e+08 | D16: Equity
B17: V | C17: =C6 -> 3.5034381e+08 | D17: Total Firm Value | F17: QUESTION # 4b
B18: New Cost of Equity (Re) | C18: =C13+(C13-C14)*(C15/C16) -> 0.10008382 | D18: Ru + (Ru - Rd) * (D / E) | F18: 100% Debt Finance Stock (Post Acquisition) | H18: Equation
B19: WACC | C19: =(C16/C17)*C18+(C15/C17)*(C14*(1-'Pre-Acquisition'!C11)) -> 0.095842661 | D19: (E/V)*Re + (D/V)*Rd*(1-T)
F20: Number of Shares Outstanding | G20: ='Pre-Acquisition'!C9 -> 8000000 | H20: Old Shares
F21: New Price Per Share | G21: =G15/G20 -> 40.417977 | H21: New Equity/# of Shares

Sheet Scenerio Analysis
C2: QUESTION # 6 1 | G2: QUESTION # 6 1 | K2: QUESTION # 6 1
C3: 100% Equity Scenario 1 | E3: Equation | G3: Shares Post Announcement | I3: Equation | K3: Shares Post Acquisition | M3: Equation
C5: Pre-Tax CF | D5: 1500000 | E5: Given | G5: Shares Outsanding | H5: ='Pre-Acquisition'!C9 -> 8000000 | I5: Old Shares | K5: Shares Outsanding | L5: =H5+H7 -> 8736202 | M5: Old Shares+Newly Issued
C6: After tax CF | D6: =D5*(1-0.25) -> 1125000 | E6: Pre-Tax * (1- .25) | G6: Share Price | H6: =H9/H5 -> 36.674742 | I6: New Firm Value/New Shares | K6: Share Price | L6: =L7/L5 -> 36.67474 | M6: New Firm Value/New Shares
C7: PV of Perpetuity | D7: =D6/'Pre-Acquisition'!C12 -> 11597938 | E7: After-Tax/Rate | G7: New Shares Required | H7: =ROUNDUP('Acquisition Info'!C5/'Scenerio Analysis'!H6,0) -> 736202 | I7: Roundup Functoin Acquisition Cost/Share Price | K7: New Firm Value | L7: ='Acquisition Info'!C5+'Scenerio Analysis'!H9 -> 3.2039794e+08 | M7: Prev firm value + Acquisition Cost
C8: NPV | D8: =D7-'Acquisition Info'!C5 -> -15402062 | E8: PV - Aqcuisition cost
G9: New Firm Value | H9: ='Pre-Acquisition'!G13+'Scenerio Analysis'!D8 -> 2.9339794e+08 | I9: Beg firm value + NPV
C12: QUESTION # 6 2 | G12: QUESTION # 6 2 | K12: QUESTION # 6 2
C13: 100% Equity Scenario 2 | E13: Equation | G13: Shares Post Announcement | I13: Equation | K13: Shares Post Acquisition | M13: Equation
C15: Pre-Tax CF | D15: 3492000 | E15: Given | G15: Shares Outsanding | H15: ='Pre-Acquisition'!C9 -> 8000000 | I15: Old Shares | K15: Shares Outsanding | L15: =H15+H17 -> 8699482 | M15: Old Shares+Newly Issued
C16: after tax CF | D16: =D15*(1-0.25) -> 2619000 | E16: Pre-Tax * (1- .25) | G16: Share Price | H16: =H19/H15 -> 38.6 | I16: New Firm Value/New Shares | K16: Share Price | L16: =L17/L15 -> 38.599999 | M16: New Firm Value/New Shares
C17: PV of Perpetuity | D17: =D16/'Pre-Acquisition'!C12 -> 27000000 | E17: After-Tax/Rate | G17: New Shares Required | H17: =ROUNDUP('Acquisition Info'!C5/'Scenerio Analysis'!H16,0) -> 699482 | I17: Roundup Functoin Acquisition Cost/Share Price | K17: New Firm Value | L17: =H19+'Acquisition Info'!C5 -> 335800000 | M17: Prev firm value + Acquisition Cost
C18: NPV | D18: =D17-'Acquisition Info'!C5 -> 0 | E18: PV - Aqcuisition cost
G19: New Firm Value | H19: ='Pre-Acquisition'!G13+'Scenerio Analysis'!D18 -> 308800000 | I19: Beg firm value + NPV
